cuparser/__init__.py
cuparser/configs.py
cuparser/parser.py
cuparser-0.0.1.dist-info/LICENSE
cuparser-0.0.1.dist-info/METADATA
cuparser-0.0.1.dist-info/WHEEL
cuparser-0.0.1.dist-info/top_level.txt
cuparser-0.0.1.dist-info/RECORD
