Metadata-Version: 2.1
Name: cuparser
Version: 0.0.1
Summary: 通用、便捷、准确的计数单位解析工具
Home-page: https://github.com/kusen-alpha/cuparser
Author: kusen
Author-email: 1194542196@qq.com
License: MIT
Project-URL: Bug Tracker, https://github.com/kusen-alpha/cuparser/issues
Project-URL: Documentation, https://github.com/kusen-alpha/cuparser/blob/master/README.md
Project-URL: Source Code, https://github.com/kusen-alpha/cuparser
Platform: any
Classifier: Programming Language :: Python :: 3
Classifier: License :: OSI Approved :: MIT License
Classifier: Operating System :: OS Independent
License-File: LICENSE
